{
    "id": 29554,
    "citation_title": "Empirical Option Pricing Models",
    "citation_author": [
        "David S. Bates"
    ],
    "citation_publication_date": "2021-12-13",
    "issue_date": "2021-12-09",
    "revision_date": "None",
    "topics": [
        "\n",
        "Financial Economics",
        "\n",
        "Financial Markets",
        "\n"
    ],
    "program": [
        "\n",
        "Asset Pricing",
        "\n"
    ],
    "projects": null,
    "working_groups": null,
    "abstract": "\n\nThis paper is an overview of empirical options research, with primary emphasis on research into systematic stochastic volatility and jump risks relevant for pricing stock index options.  The paper reviews evidence from time series analysis, option prices and option price evolution regarding those risks, and discusses required compensation.\n\n",
    "acknowledgement": "\nThis paper received no external financing other than that provided to me by the University of Iowa as a professor. The views expressed herein are those of the author and do not necessarily reflect the views of the National Bureau of Economic Research.\n\n\n"
}